{
  "supports": [
    {
      "name": "児童扶養手当",
      "conditions": {
        "single": "yes",
        "child": "yes",
        "income": "yes"
      },
      "description": "ひとり親家庭の生活安定のための手当。",
      "documents": [
        "戸籍謄本",
        "所得証明書",
        "住民票"
      ],
      "apply": "市区町村役所"
    },
    {
      "name": "ひとり親家庭医療費助成",
      "conditions": {
        "single": "yes",
        "child": "yes"
      },
      "description": "医療費の自己負担を軽減。",
      "documents": [
        "健康保険証",
        "戸籍謄本"
      ],
      "apply": "自治体福祉課"
    },
    {
      "name": "保育料減免",
      "conditions": {
        "child": "yes",
        "income": "yes",
        "child_age": "0-5"
      },
      "description": "保育園の保育料が軽減される制度。",
      "documents": [
        "保育園申請書",
        "所得証明"
      ],
      "apply": "自治体保育課"
    }
  ]
}
